{
    "УровеньСообщений": 0,
    "ЗагрузкаОбновленийРасширений": true,
    "ПутьКФайлуЛога": "F:\\github\\github\\AutoUpdateIB\\ext-update.log",
    "НаборРасширений": [
        {
            "Имя": "Исправление",
            "ПутьКФайлуОбновления": "F:\\github\\github\\AutoUpdateIB\\tests\\fixtures\\cfe\\Исправление.cfe",
            "ЗащитаОтОпасныхДействий": false
        },
        {
            "Имя": "Адаптация",
            "ПутьКФайлуОбновления": "F:\\github\\github\\AutoUpdateIB\\tests\\fixtures\\cfe\\Адаптация.cfe",
            "БезопасныйРежим": false
        },
        {
            "Имя": "Дополнение",
            "ПутьКФайлуОбновления": "F:\\github\\github\\AutoUpdateIB\\tests\\fixtures\\cfe\\Дополнение.cfe",
            "Активно": false
        }
    ]
}